[
    {
        "exchange": "MEXC",
        "coin": "LAKE",
        "ticker": "LAK3",
        "affiliate_url": "https://www.mexc.co/register?inviteCode=mexc-bicarak",
        "date_added": "2025-02-05"
    },
    {
        "exchange": "MEXC",
        "coin": "Crypto Delivery",
        "ticker": "DCOIN",
        "affiliate_url": "https://www.mexc.co/register?inviteCode=mexc-bicarak",
        "date_added": "2025-02-05"
    },
    {
        "exchange": "MEXC",
        "coin": "Whiteheart Token",
        "ticker": "WHITE",
        "affiliate_url": "https://www.mexc.co/register?inviteCode=mexc-bicarak",
        "date_added": "2025-02-05"
    },
    {
        "exchange": "MEXC",
        "coin": "Elon for AfD",
        "ticker": "ELON4AFD",
        "affiliate_url": "https://www.mexc.co/register?inviteCode=mexc-bicarak",
        "date_added": "2025-02-05"
    },
    {
        "exchange": "Gate.io",
        "coin": "BOTIFY",
        "ticker": "BOTIFY",
        "affiliate_url": "https://www.gate.io/signup/BgASAV5W?ref_type=103",
        "date_added": "2025-02-05"
    },
    {
        "exchange": "MEXC",
        "coin": "MoonEdge",
        "ticker": "MOONED",
        "affiliate_url": "https://www.mexc.co/register?inviteCode=mexc-bicarak",
        "date_added": "2025-02-05"
    }
]